MANIFEST.in
README.rst
setup.py
sm/__init__.py
sm/config.schema
sm/main.py
sm/sm.py
sm.egg-info/PKG-INFO
sm.egg-info/SOURCES.txt
sm.egg-info/dependency_links.txt
sm.egg-info/entry_points.txt
sm.egg-info/pbr.json
sm.egg-info/requires.txt
sm.egg-info/top_level.txt