Metadata-Version: 1.1
Name: sm
Version: 0.1.8
Summary: ssh host command manager tool
Home-page: https://github.com/mymonkey110/ssh-manager
Author: Michael Jiang
Author-email: mymonkey110@gmail.com
License: MIT License
Keywords: ssh,manager
Platform: UNKNOWN
Classifier: Development Status :: 4 - Beta
Classifier: License :: OSI Approved :: MIT License
Classifier: Programming Language :: Python :: 2
Classifier: Programming Language :: Python :: 2.6
Classifier: Programming Language :: Python :: 2.7
Classifier: Topic :: System :: Systems Administration
